colorpedia/__init__.py
colorpedia/cli.py
colorpedia/color.py
colorpedia/config.py
colorpedia/converters.py
colorpedia/exceptions.py
colorpedia/formatters.py
colorpedia/hexcodes.py
colorpedia/inputs.py
colorpedia/palettes.py
colorpedia/version.py
colorpedia-1.2.3.dist-info/LICENSE
colorpedia-1.2.3.dist-info/METADATA
colorpedia-1.2.3.dist-info/WHEEL
colorpedia-1.2.3.dist-info/entry_points.txt
colorpedia-1.2.3.dist-info/top_level.txt
colorpedia-1.2.3.dist-info/RECORD
