Metadata-Version: 2.1
Name: colorpedia
Version: 1.2.3
Summary: CLI for Color Lookups
Home-page: https://github.com/joowani/colorpedia
Author: Joohwan Oh
Author-email: joohwan.oh@outlook.com
License: MIT
Keywords: cli,color,terminal
Platform: UNKNOWN
Classifier: Intended Audience :: Developers
Classifier: License :: OSI Approved :: MIT License
Classifier: Natural Language :: English
Classifier: Operating System :: MacOS
Classifier: Operating System :: Microsoft :: Windows
Classifier: Operating System :: Unix
Classifier: Programming Language :: Python :: 3
Classifier: Topic :: Documentation :: Sphinx
Classifier: Topic :: Utilities
Requires-Python: >=3.6
Requires-Dist: fire (>=0.3.1)
Requires-Dist: setuptools (>=42)
Requires-Dist: setuptools-scm[toml] (>=3.4)
Requires-Dist: dataclasses (>=0.6) ; python_version < "3.7"
Provides-Extra: dev
Requires-Dist: black ; extra == 'dev'
Requires-Dist: flake8 (>=3.8.4) ; extra == 'dev'
Requires-Dist: isort (>=5.0.0) ; extra == 'dev'
Requires-Dist: mkdocs-material ; extra == 'dev'
Requires-Dist: mypy (>=0.790) ; extra == 'dev'
Requires-Dist: pre-commit (>=2.9.3) ; extra == 'dev'
Requires-Dist: pytest (>=6.0.0) ; extra == 'dev'
Requires-Dist: pytest-cov (>=2.0.0) ; extra == 'dev'
